daosim/__init__.py
daosim-0.0.5.dist-info/METADATA
daosim-0.0.5.dist-info/WHEEL
daosim-0.0.5.dist-info/licenses/LICENSE
daosim-0.0.5.dist-info/RECORD
