Metadata-Version: 2.4
Name: daosim
Version: 0.0.5
Summary: The DAG adaptation of the Onion method
Project-URL: Homepage, https://github.com/bja43/DaO_simulation
Project-URL: Issues, https://github.com/bja43/DaO_simulation
Author-email: Bryan Andrews <andr1017@umn.edu>
License: MIT
License-File: LICENSE
Classifier: License :: OSI Approved :: MIT License
Classifier: Operating System :: OS Independent
Classifier: Programming Language :: Python :: 3
Requires-Python: >=3.6
Requires-Dist: numpy>=1.20.0
